nano_banana/__init__.py
nano_banana/vision.py
nano_banana-0.4.2.dist-info/METADATA
nano_banana-0.4.2.dist-info/WHEEL
nano_banana-0.4.2.dist-info/RECORD
