Metadata-Version: 2.4
Name: nano-banana
Version: 0.4.2
Summary: Simple wrapper for Google Gemini image generation and analysis
Author-email: Simen AI <hi@simen.ai>
Keywords: ai,computer-vision,gemini,image-analysis,image-generation,openai,text-to-image
Requires-Python: >=3.8
Requires-Dist: openai>=1.106.1
